gibberish_chat_detector-0.1.2.dist-info/licenses/LICENSE
gibberish_detector/__init__.py
gibberish_detector/gibberish.py
gibberish_chat_detector-0.1.2.dist-info/METADATA
gibberish_chat_detector-0.1.2.dist-info/WHEEL
gibberish_chat_detector-0.1.2.dist-info/top_level.txt
gibberish_chat_detector-0.1.2.dist-info/RECORD
