Metadata-Version: 2.4
Name: gibberish-chat-detector
Version: 0.1.2
Summary: Detects gibberish or mischievous chat messages/string.
Author-email: Jiangang Hao <jianganghao@gmail.com>
License: MIT
Project-URL: Homepage, https://github.com/jgbrainstorm/gibberish-chat-detector
Project-URL: Repository, https://github.com/jgbrainstorm/gibberish-chat-detector
Project-URL: Issues, https://github.com/jgbrainstorm/gibberish-chat-detector/issues
Requires-Python: >=3.7
License-File: LICENSE
Requires-Dist: numpy
Dynamic: license-file
